{
  "formatVersion": 1,
  "passTypeIdentifier": "pass.ca.deloitte.tdiclaims",
  "serialNumber": "c4d4edd6-fba0-44f3-8f03-6bc1f76f714d",
  "webServiceURL": "https://8070-2001-569-729b-ee00-4937-d2ef-1877-a148.ngrok-free.app/",
  "authenticationToken": "vxwxd7J8AlNNFPS8k0a0FfUFtq0ewzFdc",
  "teamIdentifier": "539KYJTU7Y",
  "associatedStoreIdentifiers": [
    1435348849
  ],
  "organizationName": "Deloitte",
  "description": "Your Insurance Claim",
  "foregroundColor": "rgb(4, 174, 184)",
  "eventTicket": {
    "headerFields": [
      {
        "key": "header_text",
        "label": "Claims",
        "value": ""
      }
    ],
    "primaryFields": [
      {
        "key": "member",
        "value": ""
      }
    ],
    "secondaryFields": [
      {
        "key": "estimated_completion",
        "label": "ESTIMATED COMPLETION",
        "value": "2024-02-01T07:59:59.999+00:00",
        "dateStyle": "PKDateStyleLong"
      },
      {
        "key": "last_updated",
        "label": "LAST UPDATED",
        "value": "2024-01-09T05:35:02.705+00:00",
        "textAlignment": "PKTextAlignmentRight",
        "changeMessage": "Your claim CL001921 was updated on %@. For more information check out the TD Insurance App.",
        "dateStyle": "PKDateStyleLong"
      }
    ],
    "auxiliaryFields": [
      {
        "key": "claim_number",
        "label": "CLAIM NUMBER",
        "value": "CL001921"
      },
      {
        "key": "claim_handler",
        "label": "YOUR CLAIM HANDLER",
        "value": "Sophie Brown",
        "textAlignment": "PKTextAlignmentRight"
      }
    ],
    "backFields": [
      {
        "key": "your_vehicle",
        "label": "Your Vehicle",
        "value": "Mercedes"
      },
      {
        "key": "license_plate",
        "label": "License Plate",
        "value": "BEEJ 681"
      }
    ]
  },
  "type": "generic"
}